civitai_api-3.0.3.dist-info/METADATA
civitai_api-3.0.3.dist-info/WHEEL
civitai_api-3.0.3.dist-info/entry_points.txt
civitai_api/__init__.py
civitai_api/py.typed
civitai_api/v1/__init__.py
civitai_api/v1/models/base/misc.py
civitai_api/v1/models/base/modelVersion.py
civitai_api/v1/models/creators_endpoint.py
civitai_api/v1/models/images.py
civitai_api/v1/models/modelId_endpoint.py
civitai_api/v1/models/models_endpoint.py
civitai_api/v1/models/tags_endpoint.py
civitai_api/v1/models/versionId_endpoint.py
civitai_api-3.0.3.dist-info/RECORD
