Metadata-Version: 2.1
Name: civitai-api
Version: 3.0.3
Summary: Default template for PDM package
Author-Email: Pyon~ Pyon~~ <32931796+tick97115115@users.noreply.github.com>
License: MIT
Requires-Python: >=3.11
Requires-Dist: httpx[socks]>=0.28.1
Requires-Dist: pydantic>=2.10.4
